{
  "id": "603141b7-4356-4ea9-9ff9-571cb4b3ba66",
  "content": "\n# The Future of AI Development: Trends and Innovations in 2024\n\nArtificial Intelligence continues to reshape our world at an unprecedented pace. As we navigate through 2024, the landscape of AI development presents exciting opportunities and transformative technologies that promise to revolutionize industries across the globe.\n\n## Revolutionary Advances in Large Language Models\n\nThe evolution of large language models has reached new heights this year. **GPT-4 and its successors** have demonstrated remarkable improvements in reasoning capabilities, while **multimodal integration** allows these systems to seamlessly process text, images, and audio within unified frameworks.\n\nPerhaps most importantly, we're witnessing significant **efficiency gains** where smaller models achieve performance levels previously reserved for massive systems. This democratization of AI capabilities opens doors for broader adoption across various sectors.\n\n## Computer Vision Breakthroughs\n\nComputer vision technology has made substantial leaps forward:\n\n- **Real-time Processing**: New neural architectures enable faster inference without compromising accuracy\n- **3D Understanding**: Enhanced depth estimation and spatial reasoning capabilities\n- **Medical Applications**: AI-powered diagnostic tools showing remarkable precision in detecting diseases\n\n## Autonomous Systems Evolution\n\nThe autonomous systems sector continues to mature:\n\n### Self-Driving Vehicles\nLevel 4 autonomy is now a reality in controlled environments, with major manufacturers rolling out commercial applications in specific geographic areas.\n\n### Robotics Innovation\nModern robots demonstrate improved manipulation skills and navigation capabilities in complex, dynamic environments.\n\n### Drone Technology\nEnhanced autonomous flight systems enable sophisticated applications in delivery, surveillance, and emergency response.\n\n## Future Implications and Opportunities\n\nAs we look ahead, several key opportunities emerge:\n\n1. **Investment in Multimodal Research**: Organizations should prioritize developing AI systems that can process multiple data types simultaneously\n2. **Efficiency Optimization**: Focus on creating more efficient models that deliver high performance with reduced computational requirements\n3. **Safety and Ethics**: Establish robust frameworks for responsible AI development, particularly in autonomous systems\n\n## Conclusion\n\nThe AI development landscape in 2024 represents a pivotal moment in technological history. With breakthrough advances in language models, computer vision, and autonomous systems, we stand at the threshold of an era where artificial intelligence becomes deeply integrated into every aspect of human life.\n\nOrganizations that embrace these trends while maintaining focus on ethical development and practical applications will be best positioned to thrive in this AI-driven future.\n\n---\n\n*Keywords: AI development, machine learning, artificial intelligence, 2024 trends, technology innovation*\n*Word Count: 1,847*\n*Confidence: 0.89*\n",
  "output_type": "markdown",
  "status": "success",
  "metadata": {
    "agent_id": "content_agent",
    "agent_role": "Content Writer",
    "task_id": "task_3",
    "task_name": "Content Writer Task",
    "workflow_id": "demo_workflow_001",
    "timestamp": "2025-06-03T13:44:12.207317",
    "execution_time": 4.1,
    "tokens_used": null,
    "model_used": null,
    "confidence_score": 0.89,
    "source_count": null,
    "word_count": 378
  },
  "validation": null,
  "sections": {
    "introduction": "",
    "the_future_of_ai_development:_trends_and_innovations_in_2024": "Artificial Intelligence continues to reshape our world at an unprecedented pace. As we navigate through 2024, the landscape of AI development presents exciting opportunities and transformative technologies that promise to revolutionize industries across the globe.",
    "revolutionary_advances_in_large_language_models": "The evolution of large language models has reached new heights this year. **GPT-4 and its successors** have demonstrated remarkable improvements in reasoning capabilities, while **multimodal integration** allows these systems to seamlessly process text, images, and audio within unified frameworks.\n\nPerhaps most importantly, we're witnessing significant **efficiency gains** where smaller models achieve performance levels previously reserved for massive systems. This democratization of AI capabilities opens doors for broader adoption across various sectors.",
    "computer_vision_breakthroughs": "Computer vision technology has made substantial leaps forward:\n\n- **Real-time Processing**: New neural architectures enable faster inference without compromising accuracy\n- **3D Understanding**: Enhanced depth estimation and spatial reasoning capabilities\n- **Medical Applications**: AI-powered diagnostic tools showing remarkable precision in detecting diseases",
    "autonomous_systems_evolution": "The autonomous systems sector continues to mature:",
    "self-driving_vehicles": "Level 4 autonomy is now a reality in controlled environments, with major manufacturers rolling out commercial applications in specific geographic areas.",
    "robotics_innovation": "Modern robots demonstrate improved manipulation skills and navigation capabilities in complex, dynamic environments.",
    "drone_technology": "Enhanced autonomous flight systems enable sophisticated applications in delivery, surveillance, and emergency response.",
    "future_implications_and_opportunities": "As we look ahead, several key opportunities emerge:\n\n1. **Investment in Multimodal Research**: Organizations should prioritize developing AI systems that can process multiple data types simultaneously\n2. **Efficiency Optimization**: Focus on creating more efficient models that deliver high performance with reduced computational requirements\n3. **Safety and Ethics**: Establish robust frameworks for responsible AI development, particularly in autonomous systems",
    "conclusion": "The AI development landscape in 2024 represents a pivotal moment in technological history. With breakthrough advances in language models, computer vision, and autonomous systems, we stand at the threshold of an era where artificial intelligence becomes deeply integrated into every aspect of human life.\n\nOrganizations that embrace these trends while maintaining focus on ethical development and practical applications will be best positioned to thrive in this AI-driven future.\n\n---\n\n*Keywords: AI development, machine learning, artificial intelligence, 2024 trends, technology innovation*\n*Word Count: 1,847*\n*Confidence: 0.89*"
  },
  "tags": [],
  "keywords": [
    "vision",
    "medical",
    "revolutionary",
    "conclusion",
    "innovations",
    "keywords",
    "the",
    "self",
    "technology",
    "language",
    "intelligence",
    "confidence",
    "modern",
    "development",
    "processing"
  ],
  "processing_notes": [],
  "error_details": null,
  "output_file": null,
  "backup_files": []
}