{
  "id": "4ccb09c6-eeb3-422a-b425-be9e11e8e8b1",
  "content": "\n# AI Development Research Report\n\n## Executive Summary\nArtificial Intelligence development in 2024 has seen remarkable advances in several key areas including large language models, computer vision, and autonomous systems.\n\n## Key Findings\n\n### 1. Large Language Models\n- **GPT-4 and Beyond**: Continued improvements in reasoning capabilities\n- **Multimodal Integration**: Text, image, and audio processing in unified models\n- **Efficiency Gains**: Smaller models achieving comparable performance\n\n### 2. Computer Vision\n- **Real-time Processing**: New architectures enabling faster inference\n- **3D Understanding**: Improved depth estimation and spatial reasoning\n- **Medical Applications**: Enhanced diagnostic capabilities\n\n### 3. Autonomous Systems\n- **Self-Driving Cars**: Level 4 autonomy in controlled environments\n- **Robotics**: Better manipulation and navigation in complex environments\n- **Drones**: Enhanced autonomous flight capabilities\n\n## Sources\n1. OpenAI Technical Report 2024\n2. Google AI Research Publications\n3. MIT Technology Review - AI Advances\n4. Stanford AI Index Report 2024\n5. Nature Machine Intelligence Journal\n\n## Recommendations\n- Invest in multimodal AI research\n- Focus on efficiency optimization\n- Prioritize safety and ethics in autonomous systems\n\n**Confidence Score**: 0.92\n**Research Quality**: High\n",
  "output_type": "markdown",
  "status": "success",
  "metadata": {
    "agent_id": "research_agent",
    "agent_role": "Research Specialist",
    "task_id": "task_1",
    "task_name": "Research Specialist Task",
    "workflow_id": "demo_workflow_001",
    "timestamp": "2025-06-03T13:44:12.206152",
    "execution_time": 2.5,
    "tokens_used": null,
    "model_used": null,
    "confidence_score": null,
    "source_count": null,
    "word_count": 170
  },
  "validation": null,
  "sections": {
    "introduction": "",
    "ai_development_research_report": "",
    "executive_summary": "Artificial Intelligence development in 2024 has seen remarkable advances in several key areas including large language models, computer vision, and autonomous systems.",
    "key_findings": "",
    "1._large_language_models": "- **GPT-4 and Beyond**: Continued improvements in reasoning capabilities\n- **Multimodal Integration**: Text, image, and audio processing in unified models\n- **Efficiency Gains**: Smaller models achieving comparable performance",
    "2._computer_vision": "- **Real-time Processing**: New architectures enabling faster inference\n- **3D Understanding**: Improved depth estimation and spatial reasoning\n- **Medical Applications**: Enhanced diagnostic capabilities",
    "3._autonomous_systems": "- **Self-Driving Cars**: Level 4 autonomy in controlled environments\n- **Robotics**: Better manipulation and navigation in complex environments\n- **Drones**: Enhanced autonomous flight capabilities",
    "sources": "1. OpenAI Technical Report 2024\n2. Google AI Research Publications\n3. MIT Technology Review - AI Advances\n4. Stanford AI Index Report 2024\n5. Nature Machine Intelligence Journal",
    "recommendations": "- Invest in multimodal AI research\n- Focus on efficiency optimization\n- Prioritize safety and ethics in autonomous systems\n\n**Confidence Score**: 0.92\n**Research Quality**: High"
  },
  "tags": [],
  "keywords": [
    "vision",
    "executive",
    "medical",
    "review",
    "text",
    "self",
    "summary",
    "technology",
    "language",
    "intelligence",
    "confidence",
    "drones",
    "index",
    "beyond",
    "findings"
  ],
  "processing_notes": [],
  "error_details": null,
  "output_file": null,
  "backup_files": []
}